{
  "nightly": {
    "description": "Every commit to main",
    "hide": false,
    "last_updated": "2025-12-29T16:55:15.000Z",
    "last_updated_url": "https://github.com/engels74/obzorarr-docker/actions/runs/20577963338",
    "latest": false,
    "tags": [
      "nightly",
      "nightly-3060acbe7389da059268f4cac7d84566d76e8462",
      "nightly-da2010c"
    ]
  },
  "release": {
    "description": "Releases",
    "hide": false,
    "last_updated": "2025-12-23T13:46:22.000Z",
    "last_updated_url": "https://github.com/hotio/seerr/actions/runs/20462020583",
    "latest": true,
    "tags": [
      "release",
      "release-2.7.3",
      "release-9bffb63"
    ]
  }
}
